mapel/marriages/__init__.py
mapel/marriages/cultures_.py
mapel/marriages/distances_.py
mapel/marriages/features_.py
mapel/marriages/cultures/__init__.py
mapel/marriages/cultures/_utils.py
mapel/marriages/cultures/euclidean.py
mapel/marriages/cultures/impartial.py
mapel/marriages/cultures/mallows.py
mapel/marriages/cultures/urn.py
mapel/marriages/distances/__init__.py
mapel/marriages/distances/main_marriages_distances.py
mapel/marriages/features/__init__.py
mapel/marriages/features/basic_features.py
mapel/marriages/features/distance_to_stability_features.py
mapel/marriages/features/experiments_marriage.py
mapel/marriages/objects/Marriages.py
mapel/marriages/objects/MarriagesExperiment.py
mapel/marriages/objects/MarriagesFamily.py
mapel/marriages/objects/__init__.py
mapel/marriages/persistence/__init__.py
mapel/marriages/persistence/instance_exports.py
mapel/marriages/persistence/instance_imports.py
mapel_marriages-2.1.11.dist-info/LICENSE.txt
mapel_marriages-2.1.11.dist-info/METADATA
mapel_marriages-2.1.11.dist-info/WHEEL
mapel_marriages-2.1.11.dist-info/top_level.txt
mapel_marriages-2.1.11.dist-info/RECORD
