Metadata-Version: 2.1
Name: mapel-marriages
Version: 2.1.11
Summary: Map of Marriages
Author-email: Stanislaw Szufa <s.szufa@gmail.com>, Niclas Boehmer <niclas.boehmer@tu-berlin.de>
License: Copyright (c) 2018-2022 Stanislaw Szufa and contributors
Classifier: Programming Language :: Python :: 3
Classifier: License :: OSI Approved :: MIT License
Classifier: Operating System :: OS Independent
Requires-Python: >=3.7
License-File: LICENSE.txt
Requires-Dist: mapel-core >=2.0.0
